streamdeck/__init__.py
streamdeck/__main__.py
streamdeck/actions.py
streamdeck/command_sender.py
streamdeck/event_listener.py
streamdeck/manager.py
streamdeck/py.typed
streamdeck/types.py
streamdeck/websocket.py
streamdeck/models/__init__.py
streamdeck/models/configs.py
streamdeck/models/events.py
streamdeck/utils/__init__.py
streamdeck/utils/_version.py
streamdeck/utils/dirs.py
streamdeck/utils/helper_actions.py
streamdeck/utils/logging.py
streamdeck_plugin_sdk-0.5.0.dist-info/licenses/LICENSE
streamdeck_plugin_sdk-0.5.0.dist-info/METADATA
streamdeck_plugin_sdk-0.5.0.dist-info/WHEEL
streamdeck_plugin_sdk-0.5.0.dist-info/entry_points.txt
streamdeck_plugin_sdk-0.5.0.dist-info/top_level.txt
streamdeck_plugin_sdk-0.5.0.dist-info/RECORD
